gh_templates/__init__.py
gh_templates-0.1.37.dist-info/METADATA
gh_templates-0.1.37.dist-info/WHEEL
gh_templates-0.1.37.dist-info/entry_points.txt
gh_templates-0.1.37.dist-info/top_level.txt
gh_templates-0.1.37.dist-info/RECORD
